[
  {
    "id": "1",
    "danwei": "扬州公司",
    "bumen": "500千伏变电运检中心",
    "banzu_name": "变电二次检修班",
    "banzu_type": "变电二次检修",
    "name": "滕翔",
    "gender": "男",
    "dob": "2/14/1992",
    "gangwei": "班长",
    "start_date": "2013/08/02",
    "zuihao_xueli": "硕士研究生",
    "title": "高级工程师",
    "skill": "技师(继电保护员（220kV及以下）)",
    "level": "二级"
  },
  {
    "id": "2",
    "danwei": "扬州公司",
    "bumen": "500千伏变电运检中心",
    "banzu_name": "变电二次检修班",
    "banzu_type": "变电二次检修",
    "name": "徐浩",
    "gender": "男",
    "dob": "10/6/1993",
    "gangwei": "副班长",
    "start_date": "2018/08/01",
    "zuihao_xueli": "硕士研究生",
    "title": "工程师",
    "skill": "技师(继电保护员（220kV及以下）)",
    "level": "二级"
  },
  {
    "id": "3",
    "danwei": "扬州公司",
    "bumen": "500千伏变电运检中心",
    "banzu_name": "变电二次检修班",
    "banzu_type": "变电二次检修",
    "name": "样例3",
    "gender": "女",
    "dob": "1/3/1990",
    "gangwei": "见习岗",
    "start_date": "2013/08/01",
    "zuihao_xueli": "大学本科",
    "title": "助理工程师",
    "skill": "高级工(继电保护工)",
    "level": "三级"
  },
  {
    "id": "4",
    "danwei": "扬州公司",
    "bumen": "500千伏变电运检中心",
    "banzu_name": "变电二次检修班",
    "banzu_type": "变电二次检修",
    "name": "样例4",
    "gender": "男",
    "dob": "1/4/1990",
    "gangwei": "工程师",
    "start_date": "2014/08/01",
    "zuihao_xueli": "硕士研究生",
    "title": "工程师",
    "skill": "技师(送电线路工)",
    "level": "二级"
  },
  {
    "id": "5",
    "danwei": "扬州公司",
    "bumen": "500千伏变电运检中心",
    "banzu_name": "变电二次检修班",
    "banzu_type": "变电二次检修",
    "name": "样例5",
    "gender": "女",
    "dob": "1/5/1990",
    "gangwei": "工程师",
    "start_date": "2015/08/01",
    "zuihao_xueli": "大学本科",
    "title": "助理工程师",
    "skill": "高级工(继电保护工)",
    "level": "三级"
  },
  {
    "id": "6",
    "danwei": "扬州公司",
    "bumen": "500千伏变电运检中心",
    "banzu_name": "变电二次检修班",
    "banzu_type": "变电二次检修",
    "name": "样例6",
    "gender": "男",
    "dob": "1/6/1990",
    "gangwei": "见习岗",
    "start_date": "2016/08/01",
    "zuihao_xueli": "硕士研究生",
    "title": "工程师",
    "skill": "技师(送电线路工)",
    "level": "二级"
  },
  {
    "id": "7",
    "danwei": "扬州公司",
    "bumen": "500千伏变电运检中心",
    "banzu_name": "变电二次检修班",
    "banzu_type": "变电二次检修",
    "name": "样例7",
    "gender": "女",
    "dob": "1/7/1990",
    "gangwei": "工程师",
    "start_date": "2017/08/01",
    "zuihao_xueli": "大学本科",
    "title": "助理工程师",
    "skill": "高级工(继电保护工)",
    "level": "三级"
  },
  {
    "id": "8",
    "danwei": "扬州公司",
    "bumen": "500千伏变电运检中心",
    "banzu_name": "变电二次检修班",
    "banzu_type": "变电二次检修",
    "name": "样例8",
    "gender": "男",
    "dob": "1/8/1990",
    "gangwei": "工程师",
    "start_date": "2018/08/01",
    "zuihao_xueli": "硕士研究生",
    "title": "工程师",
    "skill": "技师(送电线路工)",
    "level": "二级"
  },
  {
    "id": "9",
    "danwei": "扬州公司",
    "bumen": "500千伏变电运检中心",
    "banzu_name": "变电二次检修班",
    "banzu_type": "变电二次检修",
    "name": "样例9",
    "gender": "女",
    "dob": "1/9/1990",
    "gangwei": "见习岗",
    "start_date": "2019/08/01",
    "zuihao_xueli": "大学本科",
    "title": "助理工程师",
    "skill": "高级工(继电保护工)",
    "level": "三级"
  },
  {
    "id": "10",
    "danwei": "扬州公司",
    "bumen": "变电检修中心",
    "banzu_name": "变电修试三班",
    "banzu_type": "变电修试",
    "name": "样例10",
    "gender": "男",
    "dob": "1/10/1990",
    "gangwei": "工程师",
    "start_date": "2010/08/01",
    "zuihao_xueli": "硕士研究生",
    "title": "工程师",
    "skill": "技师(送电线路工)",
    "level": "二级"
  },
  {
    "id": "11",
    "danwei": "扬州公司",
    "bumen": "变电检修中心",
    "banzu_name": "变电修试三班",
    "banzu_type": "变电修试",
    "name": "样例11",
    "gender": "女",
    "dob": "1/11/1990",
    "gangwei": "工程师",
    "start_date": "2011/08/01",
    "zuihao_xueli": "大学本科",
    "title": "助理工程师",
    "skill": "高级工(继电保护工)",
    "level": "三级"
  },
  {
    "id": "12",
    "danwei": "扬州公司",
    "bumen": "变电检修中心",
    "banzu_name": "变电修试三班",
    "banzu_type": "变电修试",
    "name": "样例12",
    "gender": "男",
    "dob": "1/12/1990",
    "gangwei": "见习岗",
    "start_date": "2012/08/01",
    "zuihao_xueli": "硕士研究生",
    "title": "工程师",
    "skill": "技师(送电线路工)",
    "level": "二级"
  },
  {
    "id": "13",
    "danwei": "扬州公司",
    "bumen": "变电检修中心",
    "banzu_name": "变电修试三班",
    "banzu_type": "变电修试",
    "name": "样例13",
    "gender": "女",
    "dob": "1/13/1990",
    "gangwei": "工程师",
    "start_date": "2013/08/01",
    "zuihao_xueli": "大学本科",
    "title": "助理工程师",
    "skill": "高级工(继电保护工)",
    "level": "三级"
  },
  {
    "id": "14",
    "danwei": "扬州公司",
    "bumen": "变电检修中心",
    "banzu_name": "变电修试三班",
    "banzu_type": "变电修试",
    "name": "样例14",
    "gender": "男",
    "dob": "1/14/1990",
    "gangwei": "工程师",
    "start_date": "2014/08/01",
    "zuihao_xueli": "硕士研究生",
    "title": "工程师",
    "skill": "技师(送电线路工)",
    "level": "二级"
  },
  {
    "id": "15",
    "danwei": "扬州公司",
    "bumen": "变电检修中心",
    "banzu_name": "变电修试三班",
    "banzu_type": "变电修试",
    "name": "样例15",
    "gender": "女",
    "dob": "1/15/1990",
    "gangwei": "见习岗",
    "start_date": "2015/08/01",
    "zuihao_xueli": "大学本科",
    "title": "助理工程师",
    "skill": "高级工(继电保护工)",
    "level": "三级"
  },
  {
    "id": "16",
    "danwei": "扬州公司",
    "bumen": "变电检修中心",
    "banzu_name": "变电修试三班",
    "banzu_type": "变电修试",
    "name": "样例16",
    "gender": "男",
    "dob": "1/16/1990",
    "gangwei": "工程师",
    "start_date": "2016/08/01",
    "zuihao_xueli": "硕士研究生",
    "title": "工程师",
    "skill": "技师(送电线路工)",
    "level": "二级"
  },
  {
    "id": "17",
    "danwei": "扬州公司",
    "bumen": "变电检修中心",
    "banzu_name": "变电修试三班",
    "banzu_type": "变电修试",
    "name": "样例17",
    "gender": "女",
    "dob": "1/17/1990",
    "gangwei": "工程师",
    "start_date": "2017/08/01",
    "zuihao_xueli": "大学本科",
    "title": "助理工程师",
    "skill": "高级工(继电保护工)",
    "level": "三级"
  },
  {
    "id": "18",
    "danwei": "扬州公司",
    "bumen": "输电运检中心",
    "banzu_name": "输电运检二班",
    "banzu_type": "输电运检",
    "name": "样例18",
    "gender": "男",
    "dob": "1/18/1990",
    "gangwei": "见习岗",
    "start_date": "2018/08/01",
    "zuihao_xueli": "硕士研究生",
    "title": "工程师",
    "skill": "技师(送电线路工)",
    "level": "二级"
  },
  {
    "id": "19",
    "danwei": "扬州公司",
    "bumen": "输电运检中心",
    "banzu_name": "输电运检二班",
    "banzu_type": "输电运检",
    "name": "样例19",
    "gender": "女",
    "dob": "1/19/1990",
    "gangwei": "工程师",
    "start_date": "2019/08/01",
    "zuihao_xueli": "大学本科",
    "title": "助理工程师",
    "skill": "高级工(继电保护工)",
    "level": "三级"
  },
  {
    "id": "20",
    "danwei": "扬州公司",
    "bumen": "输电运检中心",
    "banzu_name": "输电运检二班",
    "banzu_type": "输电运检",
    "name": "样例20",
    "gender": "男",
    "dob": "1/20/1990",
    "gangwei": "工程师",
    "start_date": "2010/08/01",
    "zuihao_xueli": "硕士研究生",
    "title": "工程师",
    "skill": "技师(送电线路工)",
    "level": "二级"
  },
  {
    "id": "21",
    "danwei": "扬州公司",
    "bumen": "输电运检中心",
    "banzu_name": "输电运检二班",
    "banzu_type": "输电运检",
    "name": "样例21",
    "gender": "女",
    "dob": "1/21/1990",
    "gangwei": "见习岗",
    "start_date": "2011/08/01",
    "zuihao_xueli": "大学本科",
    "title": "助理工程师",
    "skill": "高级工(继电保护工)",
    "level": "三级"
  },
  {
    "id": "22",
    "danwei": "扬州公司",
    "bumen": "输电运检中心",
    "banzu_name": "输电运检二班",
    "banzu_type": "输电运检",
    "name": "样例22",
    "gender": "男",
    "dob": "1/22/1990",
    "gangwei": "工程师",
    "start_date": "2012/08/01",
    "zuihao_xueli": "硕士研究生",
    "title": "工程师",
    "skill": "技师(送电线路工)",
    "level": "二级"
  },
  {
    "id": "23",
    "danwei": "扬州公司",
    "bumen": "输电运检中心",
    "banzu_name": "输电运检二班",
    "banzu_type": "输电运检",
    "name": "样例23",
    "gender": "女",
    "dob": "1/23/1990",
    "gangwei": "工程师",
    "start_date": "2013/08/01",
    "zuihao_xueli": "大学本科",
    "title": "助理工程师",
    "skill": "高级工(继电保护工)",
    "level": "三级"
  },
  {
    "id": "24",
    "danwei": "扬州公司",
    "bumen": "输电运检中心",
    "banzu_name": "输电运检二班",
    "banzu_type": "输电运检",
    "name": "样例24",
    "gender": "男",
    "dob": "1/24/1990",
    "gangwei": "见习岗",
    "start_date": "2014/08/01",
    "zuihao_xueli": "硕士研究生",
    "title": "工程师",
    "skill": "技师(送电线路工)",
    "level": "二级"
  },
  {
    "id": "25",
    "danwei": "扬州公司",
    "bumen": "输电运检中心",
    "banzu_name": "电缆运检班",
    "banzu_type": "电缆运检",
    "name": "样例25",
    "gender": "女",
    "dob": "1/25/1990",
    "gangwei": "工程师",
    "start_date": "2015/08/01",
    "zuihao_xueli": "大学本科",
    "title": "助理工程师",
    "skill": "高级工(继电保护工)",
    "level": "三级"
  },
  {
    "id": "26",
    "danwei": "扬州公司",
    "bumen": "输电运检中心",
    "banzu_name": "电缆运检班",
    "banzu_type": "电缆运检",
    "name": "样例26",
    "gender": "男",
    "dob": "1/26/1990",
    "gangwei": "工程师",
    "start_date": "2016/08/01",
    "zuihao_xueli": "硕士研究生",
    "title": "工程师",
    "skill": "技师(送电线路工)",
    "level": "二级"
  },
  {
    "id": "27",
    "danwei": "扬州公司",
    "bumen": "输电运检中心",
    "banzu_name": "电缆运检班",
    "banzu_type": "电缆运检",
    "name": "样例27",
    "gender": "女",
    "dob": "1/27/1990",
    "gangwei": "见习岗",
    "start_date": "2017/08/01",
    "zuihao_xueli": "大学本科",
    "title": "助理工程师",
    "skill": "高级工(继电保护工)",
    "level": "三级"
  },
  {
    "id": "28",
    "danwei": "扬州公司",
    "bumen": "输电运检中心",
    "banzu_name": "电缆运检班",
    "banzu_type": "电缆运检",
    "name": "样例28",
    "gender": "男",
    "dob": "1/28/1990",
    "gangwei": "见习岗",
    "start_date": "2018/08/01",
    "zuihao_xueli": "硕士研究生",
    "title": "助理工程师",
    "skill": "技师（配电线路工）",
    "level": "三级"
  },
  {
    "id": "29",
    "danwei": "扬州公司",
    "bumen": "输电运检中心",
    "banzu_name": "电缆运检班",
    "banzu_type": "电缆运检",
    "name": "样例29",
    "gender": "女",
    "dob": "1/29/1990",
    "gangwei": "工程师",
    "start_date": "2019/08/01",
    "zuihao_xueli": "大学本科",
    "title": "助理工程师",
    "skill": "高级工（配电线路工）",
    "level": "三级"
  },
  {
    "id": "30",
    "danwei": "扬州公司",
    "bumen": "输电运检中心",
    "banzu_name": "电缆运检班",
    "banzu_type": "电缆运检",
    "name": "样例30",
    "gender": "男",
    "dob": "1/30/1990",
    "gangwei": "工程师",
    "start_date": "2010/08/01",
    "zuihao_xueli": "硕士研究生",
    "title": "工程师",
    "skill": "技师（配电线路工）",
    "level": "四级"
  },
  {
    "id": "31",
    "danwei": "扬州公司",
    "bumen": "城西供电服务中心",
    "banzu_name": "低压综合服务二班",
    "banzu_type": "配电运检/配电二次运检/低压综合服务",
    "name": "样例31",
    "gender": "女",
    "dob": "1/31/1990",
    "gangwei": "工程师",
    "start_date": "2011/08/01",
    "zuihao_xueli": "大学本科",
    "title": "助理工程师",
    "skill": "高级工（配电线路工）",
    "level": "三级"
  },
  {
    "id": "32",
    "danwei": "扬州公司",
    "bumen": "城西供电服务中心",
    "banzu_name": "低压综合服务二班",
    "banzu_type": "配电运检/配电二次运检/低压综合服务",
    "name": "样例32",
    "gender": "男",
    "dob": "1/32/1990",
    "gangwei": "见习岗",
    "start_date": "2012/08/01",
    "zuihao_xueli": "硕士研究生",
    "title": "助理工程师",
    "skill": "技师（配电线路工）",
    "level": "三级"
  },
  {
    "id": "33",
    "danwei": "扬州公司",
    "bumen": "城西供电服务中心",
    "banzu_name": "低压综合服务二班",
    "banzu_type": "配电运检/配电二次运检/低压综合服务",
    "name": "样例33",
    "gender": "女",
    "dob": "1/33/1990",
    "gangwei": "工程师",
    "start_date": "2013/08/01",
    "zuihao_xueli": "大学本科",
    "title": "工程师",
    "skill": "高级工（配电线路工）",
    "level": "三级"
  },
  {
    "id": "34",
    "danwei": "扬州公司",
    "bumen": "城西供电服务中心",
    "banzu_name": "低压综合服务二班",
    "banzu_type": "配电运检/配电二次运检/低压综合服务",
    "name": "样例34",
    "gender": "男",
    "dob": "1/34/1990",
    "gangwei": "工程师",
    "start_date": "2014/08/01",
    "zuihao_xueli": "硕士研究生",
    "title": "助理工程师",
    "skill": "技师（配电线路工）",
    "level": "三级"
  },
  {
    "id": "35",
    "danwei": "扬州公司",
    "bumen": "城西供电服务中心",
    "banzu_name": "低压综合服务二班",
    "banzu_type": "配电运检/配电二次运检/低压综合服务",
    "name": "样例35",
    "gender": "女",
    "dob": "1/35/1990",
    "gangwei": "工程师",
    "start_date": "2015/08/01",
    "zuihao_xueli": "大学本科",
    "title": "助理工程师",
    "skill": "高级工（配电线路工）",
    "level": "四级"
  },
  {
    "id": "36",
    "danwei": "扬州公司",
    "bumen": "城西供电服务中心",
    "banzu_name": "低压综合服务二班",
    "banzu_type": "配电运检/配电二次运检/低压综合服务",
    "name": "样例36",
    "gender": "男",
    "dob": "1/36/1990",
    "gangwei": "见习岗",
    "start_date": "2016/08/01",
    "zuihao_xueli": "硕士研究生",
    "title": "工程师",
    "skill": "技师（配电线路工）",
    "level": "三级"
  },
  {
    "id": "37",
    "danwei": "扬州公司",
    "bumen": "城西供电服务中心",
    "banzu_name": "低压综合服务二班",
    "banzu_type": "配电运检/配电二次运检/低压综合服务",
    "name": "样例37",
    "gender": "女",
    "dob": "1/37/1990",
    "gangwei": "工程师",
    "start_date": "2017/08/01",
    "zuihao_xueli": "大学本科",
    "title": "助理工程师",
    "skill": "高级工（配电线路工）",
    "level": "三级"
  },
  {
    "id": "38",
    "danwei": "扬州公司",
    "bumen": "城东供电服务中心",
    "banzu_name": "低压综合服务二班",
    "banzu_type": "配电运检/配电二次运检/低压综合服务",
    "name": "样例38",
    "gender": "男",
    "dob": "1/38/1990",
    "gangwei": "工程师",
    "start_date": "2018/08/01",
    "zuihao_xueli": "硕士研究生",
    "title": "助理工程师",
    "skill": "技师（配电线路工）",
    "level": "三级"
  },
  {
    "id": "39",
    "danwei": "扬州公司",
    "bumen": "城东供电服务中心",
    "banzu_name": "低压综合服务二班",
    "banzu_type": "配电运检/配电二次运检/低压综合服务",
    "name": "样例39",
    "gender": "女",
    "dob": "1/39/1990",
    "gangwei": "工程师",
    "start_date": "2019/08/01",
    "zuihao_xueli": "大学本科",
    "title": "工程师",
    "skill": "高级工（配电线路工）",
    "level": "三级"
  },
  {
    "id": "40",
    "danwei": "扬州公司",
    "bumen": "城东供电服务中心",
    "banzu_name": "低压综合服务二班",
    "banzu_type": "配电运检/配电二次运检/低压综合服务",
    "name": "样例40",
    "gender": "男",
    "dob": "1/40/1990",
    "gangwei": "见习岗",
    "start_date": "2010/08/01",
    "zuihao_xueli": "硕士研究生",
    "title": "助理工程师",
    "skill": "技师（配电线路工）",
    "level": "四级"
  },
  {
    "id": "41",
    "danwei": "扬州公司",
    "bumen": "城东供电服务中心",
    "banzu_name": "低压综合服务二班",
    "banzu_type": "配电运检/配电二次运检/低压综合服务",
    "name": "样例41",
    "gender": "女",
    "dob": "1/41/1990",
    "gangwei": "工程师",
    "start_date": "2011/08/01",
    "zuihao_xueli": "大学本科",
    "title": "助理工程师",
    "skill": "高级工（配电线路工）",
    "level": "三级"
  },
  {
    "id": "42",
    "danwei": "扬州公司",
    "bumen": "城东供电服务中心",
    "banzu_name": "低压综合服务二班",
    "banzu_type": "配电运检/配电二次运检/低压综合服务",
    "name": "样例42",
    "gender": "男",
    "dob": "1/42/1990",
    "gangwei": "工程师",
    "start_date": "2012/08/01",
    "zuihao_xueli": "硕士研究生",
    "title": "工程师",
    "skill": "技师（配电线路工）",
    "level": "三级"
  },
  {
    "id": "43",
    "danwei": "扬州公司",
    "bumen": "城东供电服务中心",
    "banzu_name": "低压综合服务二班",
    "banzu_type": "配电运检/配电二次运检/低压综合服务",
    "name": "样例43",
    "gender": "女",
    "dob": "1/43/1990",
    "gangwei": "工程师",
    "start_date": "2013/08/01",
    "zuihao_xueli": "大学本科",
    "title": "助理工程师",
    "skill": "高级工（配电线路工）",
    "level": "三级"
  },
  {
    "id": "44",
    "danwei": "扬州公司",
    "bumen": "城东供电服务中心",
    "banzu_name": "低压综合服务二班",
    "banzu_type": "配电运检/配电二次运检/低压综合服务",
    "name": "样例44",
    "gender": "男",
    "dob": "1/44/1990",
    "gangwei": "见习岗",
    "start_date": "2014/08/01",
    "zuihao_xueli": "硕士研究生",
    "title": "助理工程师",
    "skill": "技师（配电线路工）",
    "level": "三级"
  },
  {
    "id": "45",
    "danwei": "扬州公司",
    "bumen": "信息通信分公司（数据中心）",
    "banzu_name": "信通运检一班",
    "banzu_type": "信通运检（通信）",
    "name": "样例45",
    "gender": "女",
    "dob": "1/45/1990",
    "gangwei": "工程师",
    "start_date": "2015/08/01",
    "zuihao_xueli": "大学本科",
    "title": "工程师",
    "skill": "高级工（配电线路工）",
    "level": "四级"
  },
  {
    "id": "46",
    "danwei": "扬州公司",
    "bumen": "信息通信分公司（数据中心）",
    "banzu_name": "信通运检一班",
    "banzu_type": "信通运检（通信）",
    "name": "样例46",
    "gender": "男",
    "dob": "1/46/1990",
    "gangwei": "工程师",
    "start_date": "2016/08/01",
    "zuihao_xueli": "硕士研究生",
    "title": "助理工程师",
    "skill": "技师（配电线路工）",
    "level": "三级"
  },
  {
    "id": "47",
    "danwei": "扬州公司",
    "bumen": "信息通信分公司（数据中心）",
    "banzu_name": "信通运检一班",
    "banzu_type": "信通运检（通信）",
    "name": "样例47",
    "gender": "女",
    "dob": "1/47/1990",
    "gangwei": "工程师",
    "start_date": "2017/08/01",
    "zuihao_xueli": "大学本科",
    "title": "助理工程师",
    "skill": "高级工（配电线路工）",
    "level": "三级"
  },
  {
    "id": "48",
    "danwei": "扬州公司",
    "bumen": "信息通信分公司（数据中心）",
    "banzu_name": "信通运检一班",
    "banzu_type": "信通运检（通信）",
    "name": "样例48",
    "gender": "男",
    "dob": "1/48/1990",
    "gangwei": "见习岗",
    "start_date": "2018/08/01",
    "zuihao_xueli": "硕士研究生",
    "title": "工程师",
    "skill": "技师（配电线路工）",
    "level": "三级"
  },
  {
    "id": "49",
    "danwei": "扬州公司",
    "bumen": "信息通信分公司（数据中心）",
    "banzu_name": "信通运检一班",
    "banzu_type": "信通运检（通信）",
    "name": "样例49",
    "gender": "女",
    "dob": "1/49/1990",
    "gangwei": "工程师",
    "start_date": "2019/08/01",
    "zuihao_xueli": "大学本科",
    "title": "助理工程师",
    "skill": "高级工（配电线路工）",
    "level": "三级"
  },
  {
    "id": "50",
    "danwei": "扬州公司",
    "bumen": "信息通信分公司（数据中心）",
    "banzu_name": "信通运检二班",
    "banzu_type": "信通运检（数字化）",
    "name": "样例50",
    "gender": "男",
    "dob": "1/50/1990",
    "gangwei": "工程师",
    "start_date": "2010/08/01",
    "zuihao_xueli": "硕士研究生",
    "title": "助理工程师",
    "skill": "技师（配电线路工）",
    "level": "四级"
  },
  {
    "id": "51",
    "danwei": "扬州公司",
    "bumen": "信息通信分公司（数据中心）",
    "banzu_name": "信通运检二班",
    "banzu_type": "信通运检（数字化）",
    "name": "样例51",
    "gender": "女",
    "dob": "1/51/1990",
    "gangwei": "工程师",
    "start_date": "2011/08/01",
    "zuihao_xueli": "大学本科",
    "title": "工程师",
    "skill": "高级工（配电线路工）",
    "level": "三级"
  },
  {
    "id": "52",
    "danwei": "扬州公司",
    "bumen": "信息通信分公司（数据中心）",
    "banzu_name": "信通运检二班",
    "banzu_type": "信通运检（数字化）",
    "name": "样例52",
    "gender": "男",
    "dob": "1/52/1990",
    "gangwei": "见习岗",
    "start_date": "2012/08/01",
    "zuihao_xueli": "硕士研究生",
    "title": "助理工程师",
    "skill": "技师（配电线路工）",
    "level": "三级"
  },
  {
    "id": "53",
    "danwei": "扬州公司",
    "bumen": "信息通信分公司（数据中心）",
    "banzu_name": "信通运检二班",
    "banzu_type": "信通运检（数字化）",
    "name": "样例53",
    "gender": "女",
    "dob": "1/53/1990",
    "gangwei": "工程师",
    "start_date": "2013/08/01",
    "zuihao_xueli": "大学本科",
    "title": "助理工程师",
    "skill": "高级工（配电线路工）",
    "level": "三级"
  },
  {
    "id": "54",
    "danwei": "扬州公司",
    "bumen": "信息通信分公司（数据中心）",
    "banzu_name": "信通运检二班",
    "banzu_type": "信通运检（数字化）",
    "name": "样例54",
    "gender": "男",
    "dob": "1/54/1990",
    "gangwei": "工程师",
    "start_date": "2014/08/01",
    "zuihao_xueli": "硕士研究生",
    "title": "工程师",
    "skill": "技师（配电线路工）",
    "level": "三级"
  },
  {
    "id": "55",
    "danwei": "扬州公司",
    "bumen": "信息通信分公司（数据中心）",
    "banzu_name": "信通运检二班",
    "banzu_type": "信通运检（数字化）",
    "name": "样例55",
    "gender": "女",
    "dob": "1/55/1990",
    "gangwei": "工程师",
    "start_date": "2015/08/01",
    "zuihao_xueli": "大学本科",
    "title": "助理工程师",
    "skill": "高级工（配电线路工）",
    "level": "四级"
  },
  {
    "id": "56",
    "danwei": "扬州公司",
    "bumen": "输变电运检中心",
    "banzu_name": "变电检修班",
    "banzu_type": "变电修试",
    "name": "样例56",
    "gender": "男",
    "dob": "1/56/1990",
    "gangwei": "见习岗",
    "start_date": "2016/08/01",
    "zuihao_xueli": "硕士研究生",
    "title": "助理工程师",
    "skill": "技师（配电线路工）",
    "level": "三级"
  },
  {
    "id": "57",
    "danwei": "江都公司",
    "bumen": "输变电运检中心",
    "banzu_name": "变电检修班",
    "banzu_type": "变电修试",
    "name": "样例57",
    "gender": "女",
    "dob": "1/57/1990",
    "gangwei": "工程师",
    "start_date": "2017/08/01",
    "zuihao_xueli": "大学本科",
    "title": "工程师",
    "skill": "高级工（配电线路工）",
    "level": "三级"
  },
  {
    "id": "58",
    "danwei": "江都公司",
    "bumen": "输变电运检中心",
    "banzu_name": "变电检修班",
    "banzu_type": "变电修试",
    "name": "样例58",
    "gender": "男",
    "dob": "1/58/1990",
    "gangwei": "工程师",
    "start_date": "2018/08/01",
    "zuihao_xueli": "硕士研究生",
    "title": "助理工程师",
    "skill": "技师（配电线路工）",
    "level": "三级"
  },
  {
    "id": "59",
    "danwei": "江都公司",
    "bumen": "输变电运检中心",
    "banzu_name": "变电检修班",
    "banzu_type": "变电修试",
    "name": "样例59",
    "gender": "女",
    "dob": "1/59/1990",
    "gangwei": "工程师",
    "start_date": "2019/08/01",
    "zuihao_xueli": "大学本科",
    "title": "助理工程师",
    "skill": "高级工（配电线路工）",
    "level": "三级"
  },
  {
    "id": "60",
    "danwei": "江都公司",
    "bumen": "输变电运检中心",
    "banzu_name": "变电检修班",
    "banzu_type": "变电修试",
    "name": "样例60",
    "gender": "男",
    "dob": "1/60/1990",
    "gangwei": "见习岗",
    "start_date": "2010/08/01",
    "zuihao_xueli": "硕士研究生",
    "title": "工程师",
    "skill": "技师（配电线路工）",
    "level": "四级"
  },
  {
    "id": "61",
    "danwei": "江都公司",
    "bumen": "输变电运检中心",
    "banzu_name": "变电检修班",
    "banzu_type": "变电修试",
    "name": "样例61",
    "gender": "女",
    "dob": "1/61/1990",
    "gangwei": "工程师",
    "start_date": "2011/08/01",
    "zuihao_xueli": "大学本科",
    "title": "助理工程师",
    "skill": "高级工（配电线路工）",
    "level": "三级"
  },
  {
    "id": "62",
    "danwei": "江都公司",
    "bumen": "配电运检中心（项目管理分中心）",
    "banzu_name": "配电运检一班",
    "banzu_type": "配电运检",
    "name": "样例62",
    "gender": "男",
    "dob": "1/62/1990",
    "gangwei": "工程师",
    "start_date": "2012/08/01",
    "zuihao_xueli": "硕士研究生",
    "title": "助理工程师",
    "skill": "技师（配电线路工）",
    "level": "三级"
  },
  {
    "id": "63",
    "danwei": "江都公司",
    "bumen": "配电运检中心（项目管理分中心）",
    "banzu_name": "配电运检一班",
    "banzu_type": "配电运检",
    "name": "样例63",
    "gender": "女",
    "dob": "1/63/1990",
    "gangwei": "工程师",
    "start_date": "2013/08/01",
    "zuihao_xueli": "大学本科",
    "title": "工程师",
    "skill": "高级工（配电线路工）",
    "level": "三级"
  },
  {
    "id": "64",
    "danwei": "江都公司",
    "bumen": "配电运检中心（项目管理分中心）",
    "banzu_name": "配电运检一班",
    "banzu_type": "配电运检",
    "name": "样例64",
    "gender": "男",
    "dob": "1/64/1990",
    "gangwei": "见习岗",
    "start_date": "2014/08/01",
    "zuihao_xueli": "硕士研究生",
    "title": "助理工程师",
    "skill": "技师（配电线路工）",
    "level": "三级"
  },
  {
    "id": "65",
    "danwei": "江都公司",
    "bumen": "配电运检中心（项目管理分中心）",
    "banzu_name": "配电运检一班",
    "banzu_type": "配电运检",
    "name": "样例65",
    "gender": "女",
    "dob": "1/65/1990",
    "gangwei": "工程师",
    "start_date": "2015/08/01",
    "zuihao_xueli": "大学本科",
    "title": "助理工程师",
    "skill": "高级工（配电线路工）",
    "level": "四级"
  },
  {
    "id": "66",
    "danwei": "江都公司",
    "bumen": "配电运检中心（项目管理分中心）",
    "banzu_name": "配电运检一班",
    "banzu_type": "配电运检",
    "name": "样例66",
    "gender": "男",
    "dob": "1/66/1990",
    "gangwei": "工程师",
    "start_date": "2016/08/01",
    "zuihao_xueli": "硕士研究生",
    "title": "工程师",
    "skill": "技师（配电线路工）",
    "level": "三级"
  },
  {
    "id": "67",
    "danwei": "江都公司",
    "bumen": "配电运检中心（项目管理分中心）",
    "banzu_name": "配电运检一班",
    "banzu_type": "配电运检",
    "name": "样例67",
    "gender": "女",
    "dob": "1/67/1990",
    "gangwei": "工程师",
    "start_date": "2017/08/01",
    "zuihao_xueli": "大学本科",
    "title": "助理工程师",
    "skill": "高级工（配电线路工）",
    "level": "三级"
  },
  {
    "id": "68",
    "danwei": "仪征公司",
    "bumen": "配电运检中心（项目管理分中心）",
    "banzu_name": "配电运检一班",
    "banzu_type": "配电运检",
    "name": "样例68",
    "gender": "男",
    "dob": "1/68/1990",
    "gangwei": "见习岗",
    "start_date": "2018/08/01",
    "zuihao_xueli": "硕士研究生",
    "title": "助理工程师",
    "skill": "技师（配电线路工）",
    "level": "三级"
  },
  {
    "id": "69",
    "danwei": "仪征公司",
    "bumen": "配电运检中心（项目管理分中心）",
    "banzu_name": "配电运检一班",
    "banzu_type": "配电运检",
    "name": "样例69",
    "gender": "女",
    "dob": "1/69/1990",
    "gangwei": "工程师",
    "start_date": "2019/08/01",
    "zuihao_xueli": "大学本科",
    "title": "工程师",
    "skill": "高级工（配电线路工）",
    "level": "三级"
  },
  {
    "id": "70",
    "danwei": "仪征公司",
    "bumen": "配电运检中心（项目管理分中心）",
    "banzu_name": "配电运检一班",
    "banzu_type": "配电运检",
    "name": "样例70",
    "gender": "男",
    "dob": "1/70/1990",
    "gangwei": "工程师",
    "start_date": "2010/08/01",
    "zuihao_xueli": "硕士研究生",
    "title": "助理工程师",
    "skill": "技师（配电线路工）",
    "level": "四级"
  },
  {
    "id": "71",
    "danwei": "仪征公司",
    "bumen": "配电运检中心（项目管理分中心）",
    "banzu_name": "配电运检二班",
    "banzu_type": "配电运检",
    "name": "样例71",
    "gender": "女",
    "dob": "1/71/1990",
    "gangwei": "工程师",
    "start_date": "2011/08/01",
    "zuihao_xueli": "大学本科",
    "title": "助理工程师",
    "skill": "高级工（配电线路工）",
    "level": "三级"
  },
  {
    "id": "72",
    "danwei": "仪征公司",
    "bumen": "配电运检中心（项目管理分中心）",
    "banzu_name": "配电运检二班",
    "banzu_type": "配电运检",
    "name": "样例72",
    "gender": "男",
    "dob": "1/72/1990",
    "gangwei": "见习岗",
    "start_date": "2012/08/01",
    "zuihao_xueli": "硕士研究生",
    "title": "工程师",
    "skill": "技师（配电线路工）",
    "level": "三级"
  },
  {
    "id": "73",
    "danwei": "仪征公司",
    "bumen": "配电运检中心（项目管理分中心）",
    "banzu_name": "配电运检二班",
    "banzu_type": "配电运检",
    "name": "样例73",
    "gender": "女",
    "dob": "1/73/1990",
    "gangwei": "工程师",
    "start_date": "2013/08/01",
    "zuihao_xueli": "大学本科",
    "title": "助理工程师",
    "skill": "高级工（配电线路工）",
    "level": "三级"
  },
  {
    "id": "74",
    "danwei": "仪征公司",
    "bumen": "配电运检中心（项目管理分中心）",
    "banzu_name": "配电运检二班",
    "banzu_type": "配电运检",
    "name": "样例74",
    "gender": "男",
    "dob": "1/74/1990",
    "gangwei": "工程师",
    "start_date": "2014/08/01",
    "zuihao_xueli": "硕士研究生",
    "title": "助理工程师",
    "skill": "技师（配电线路工）",
    "level": "三级"
  },
  {
    "id": "75",
    "danwei": "仪征公司",
    "bumen": "配电运检中心（项目管理分中心）",
    "banzu_name": "配电运检二班",
    "banzu_type": "配电运检",
    "name": "样例75",
    "gender": "女",
    "dob": "1/75/1990",
    "gangwei": "工程师",
    "start_date": "2015/08/01",
    "zuihao_xueli": "大学本科",
    "title": "工程师",
    "skill": "高级工（配电线路工）",
    "level": "四级"
  },
  {
    "id": "76",
    "danwei": "仪征公司",
    "bumen": "配电运检中心（项目管理分中心）",
    "banzu_name": "配电运检二班",
    "banzu_type": "配电运检",
    "name": "样例76",
    "gender": "男",
    "dob": "1/76/1990",
    "gangwei": "见习岗",
    "start_date": "2016/08/01",
    "zuihao_xueli": "硕士研究生",
    "title": "助理工程师",
    "skill": "技师（配电线路工）",
    "level": "三级"
  },
  {
    "id": "77",
    "danwei": "仪征公司",
    "bumen": "配电运检中心（项目管理分中心）",
    "banzu_name": "配电运检二班",
    "banzu_type": "配电运检",
    "name": "样例77",
    "gender": "女",
    "dob": "1/77/1990",
    "gangwei": "工程师",
    "start_date": "2017/08/01",
    "zuihao_xueli": "大学本科",
    "title": "助理工程师",
    "skill": "高级工（配电线路工）",
    "level": "三级"
  },
  {
    "id": "78",
    "danwei": "仪征公司",
    "bumen": "配电运检中心（项目管理分中心）",
    "banzu_name": "配电运检二班",
    "banzu_type": "配电运检",
    "name": "样例78",
    "gender": "男",
    "dob": "1/78/1990",
    "gangwei": "工程师",
    "start_date": "2018/08/01",
    "zuihao_xueli": "硕士研究生",
    "title": "工程师",
    "skill": "技师（配电线路工）",
    "level": "三级"
  },
  {
    "id": "79",
    "danwei": "仪征公司",
    "bumen": "配电运检中心（项目管理分中心）",
    "banzu_name": "配电运检二班",
    "banzu_type": "配电运检",
    "name": "样例79",
    "gender": "女",
    "dob": "1/79/1990",
    "gangwei": "工程师",
    "start_date": "2019/08/01",
    "zuihao_xueli": "大学本科",
    "title": "助理工程师",
    "skill": "高级工（配电线路工）",
    "level": "三级"
  },
  {
    "id": "80",
    "danwei": "仪征公司",
    "bumen": "配电运检中心（项目管理分中心）",
    "banzu_name": "配电运检二班",
    "banzu_type": "配电运检",
    "name": "样例80",
    "gender": "男",
    "dob": "1/80/1990",
    "gangwei": "见习岗",
    "start_date": "2010/08/01",
    "zuihao_xueli": "硕士研究生",
    "title": "助理工程师",
    "skill": "技师（配电线路工）",
    "level": "四级"
  },
  {
    "id": "81",
    "danwei": "仪征公司",
    "bumen": "配电运检中心（项目管理分中心）",
    "banzu_name": "配电运检二班",
    "banzu_type": "配电运检",
    "name": "样例81",
    "gender": "女",
    "dob": "1/81/1990",
    "gangwei": "工程师",
    "start_date": "2011/08/01",
    "zuihao_xueli": "大学本科",
    "title": "工程师",
    "skill": "高级工（配电线路工）",
    "level": "三级"
  },
  {
    "id": "82",
    "danwei": "仪征公司",
    "bumen": "配电运检中心（项目管理分中心）",
    "banzu_name": "配电运检二班",
    "banzu_type": "配电运检",
    "name": "样例82",
    "gender": "男",
    "dob": "1/82/1990",
    "gangwei": "工程师",
    "start_date": "2012/08/01",
    "zuihao_xueli": "硕士研究生",
    "title": "助理工程师",
    "skill": "技师（配电线路工）",
    "level": "三级"
  },
  {
    "id": "83",
    "danwei": "仪征公司",
    "bumen": "配电运检中心（项目管理分中心）",
    "banzu_name": "配电运检二班",
    "banzu_type": "配电运检",
    "name": "样例83",
    "gender": "女",
    "dob": "1/83/1990",
    "gangwei": "工程师",
    "start_date": "2013/08/01",
    "zuihao_xueli": "大学本科",
    "title": "助理工程师",
    "skill": "高级工（配电线路工）",
    "level": "三级"
  },
  {
    "id": "84",
    "danwei": "仪征公司",
    "bumen": "配电运检中心（项目管理分中心）",
    "banzu_name": "配电运检二班",
    "banzu_type": "配电运检",
    "name": "样例84",
    "gender": "男",
    "dob": "1/84/1990",
    "gangwei": "见习岗",
    "start_date": "2014/08/01",
    "zuihao_xueli": "硕士研究生",
    "title": "工程师",
    "skill": "技师（配电线路工）",
    "level": "三级"
  },
  {
    "id": "85",
    "danwei": "高邮公司",
    "bumen": "配电运检中心（项目管理分中心）",
    "banzu_name": "配电运检二班",
    "banzu_type": "配电运检",
    "name": "样例85",
    "gender": "女",
    "dob": "1/85/1990",
    "gangwei": "工程师",
    "start_date": "2015/08/01",
    "zuihao_xueli": "大学本科",
    "title": "助理工程师",
    "skill": "高级工（配电线路工）",
    "level": "四级"
  },
  {
    "id": "86",
    "danwei": "高邮公司",
    "bumen": "配电运检中心（项目管理分中心）",
    "banzu_name": "配电运检二班",
    "banzu_type": "配电运检",
    "name": "样例86",
    "gender": "男",
    "dob": "1/86/1990",
    "gangwei": "工程师",
    "start_date": "2016/08/01",
    "zuihao_xueli": "硕士研究生",
    "title": "助理工程师",
    "skill": "技师（配电线路工）",
    "level": "三级"
  },
  {
    "id": "87",
    "danwei": "高邮公司",
    "bumen": "配电运检中心（项目管理分中心）",
    "banzu_name": "配电运检二班",
    "banzu_type": "配电运检",
    "name": "样例87",
    "gender": "女",
    "dob": "1/87/1990",
    "gangwei": "工程师",
    "start_date": "2017/08/01",
    "zuihao_xueli": "大学本科",
    "title": "工程师",
    "skill": "高级工（配电线路工）",
    "level": "三级"
  },
  {
    "id": "88",
    "danwei": "高邮公司",
    "bumen": "配电运检中心（项目管理分中心）",
    "banzu_name": "配电运检二班",
    "banzu_type": "配电运检",
    "name": "样例88",
    "gender": "男",
    "dob": "1/88/1990",
    "gangwei": "见习岗",
    "start_date": "2018/08/01",
    "zuihao_xueli": "硕士研究生",
    "title": "助理工程师",
    "skill": "技师（配电线路工）",
    "level": "三级"
  },
  {
    "id": "89",
    "danwei": "高邮公司",
    "bumen": "配电运检中心（项目管理分中心）",
    "banzu_name": "配电运检二班",
    "banzu_type": "配电运检",
    "name": "样例89",
    "gender": "女",
    "dob": "1/89/1990",
    "gangwei": "工程师",
    "start_date": "2019/08/01",
    "zuihao_xueli": "大学本科",
    "title": "助理工程师",
    "skill": "高级工（配电线路工）",
    "level": "三级"
  },
  {
    "id": "90",
    "danwei": "高邮公司",
    "bumen": "配电运检中心（项目管理分中心）",
    "banzu_name": "配电运检二班",
    "banzu_type": "配电运检",
    "name": "样例90",
    "gender": "男",
    "dob": "1/90/1990",
    "gangwei": "工程师",
    "start_date": "2010/08/01",
    "zuihao_xueli": "硕士研究生",
    "title": "工程师",
    "skill": "技师（配电线路工）",
    "level": "四级"
  },
  {
    "id": "91",
    "danwei": "高邮公司",
    "bumen": "配电运检中心（项目管理分中心）",
    "banzu_name": "配电运检二班",
    "banzu_type": "配电运检",
    "name": "样例91",
    "gender": "女",
    "dob": "1/91/1990",
    "gangwei": "工程师",
    "start_date": "2011/08/01",
    "zuihao_xueli": "大学本科",
    "title": "助理工程师",
    "skill": "高级工（配电线路工）",
    "level": "三级"
  },
  {
    "id": "92",
    "danwei": "高邮公司",
    "bumen": "配电运检中心（项目管理分中心）",
    "banzu_name": "配电运检二班",
    "banzu_type": "配电运检",
    "name": "样例92",
    "gender": "男",
    "dob": "1/92/1990",
    "gangwei": "见习岗",
    "start_date": "2012/08/01",
    "zuihao_xueli": "硕士研究生",
    "title": "助理工程师",
    "skill": "技师（配电线路工）",
    "level": "三级"
  },
  {
    "id": "93",
    "danwei": "高邮公司",
    "bumen": "配电运检中心（项目管理分中心）",
    "banzu_name": "配电运检二班",
    "banzu_type": "配电运检",
    "name": "样例93",
    "gender": "女",
    "dob": "1/93/1990",
    "gangwei": "工程师",
    "start_date": "2013/08/01",
    "zuihao_xueli": "大学本科",
    "title": "工程师",
    "skill": "高级工（配电线路工）",
    "level": "三级"
  },
  {
    "id": "94",
    "danwei": "高邮公司",
    "bumen": "配电运检中心（项目管理分中心）",
    "banzu_name": "配电运检二班",
    "banzu_type": "配电运检",
    "name": "样例94",
    "gender": "男",
    "dob": "1/94/1990",
    "gangwei": "工程师",
    "start_date": "2014/08/01",
    "zuihao_xueli": "硕士研究生",
    "title": "助理工程师",
    "skill": "技师（配电线路工）",
    "level": "三级"
  },
  {
    "id": "95",
    "danwei": "高邮公司",
    "bumen": "配电运检中心（项目管理分中心）",
    "banzu_name": "配电运检二班",
    "banzu_type": "配电运检",
    "name": "样例95",
    "gender": "女",
    "dob": "1/95/1990",
    "gangwei": "工程师",
    "start_date": "2015/08/01",
    "zuihao_xueli": "大学本科",
    "title": "助理工程师",
    "skill": "高级工（配电线路工）",
    "level": "四级"
  },
  {
    "id": "96",
    "danwei": "高邮公司",
    "bumen": "配电运检中心（项目管理分中心）",
    "banzu_name": "配电运检二班",
    "banzu_type": "配电运检",
    "name": "样例96",
    "gender": "男",
    "dob": "1/96/1990",
    "gangwei": "见习岗",
    "start_date": "2016/08/01",
    "zuihao_xueli": "硕士研究生",
    "title": "工程师",
    "skill": "技师（配电线路工）",
    "level": "三级"
  },
  {
    "id": "97",
    "danwei": "高邮公司",
    "bumen": "配电运检中心（项目管理分中心）",
    "banzu_name": "配电运检二班",
    "banzu_type": "配电运检",
    "name": "样例97",
    "gender": "女",
    "dob": "1/97/1990",
    "gangwei": "工程师",
    "start_date": "2017/08/01",
    "zuihao_xueli": "大学本科",
    "title": "助理工程师",
    "skill": "高级工（配电线路工）",
    "level": "三级"
  },
  {
    "id": "98",
    "danwei": "高邮公司",
    "bumen": "配电运检中心（项目管理分中心）",
    "banzu_name": "配电运检二班",
    "banzu_type": "配电运检",
    "name": "样例98",
    "gender": "男",
    "dob": "1/98/1990",
    "gangwei": "工程师",
    "start_date": "2018/08/01",
    "zuihao_xueli": "硕士研究生",
    "title": "助理工程师",
    "skill": "技师（配电线路工）",
    "level": "三级"
  },
  {
    "id": "99",
    "danwei": "宝应公司",
    "bumen": "配电运检中心（项目管理分中心）",
    "banzu_name": "配电运检班",
    "banzu_type": "配电运检",
    "name": "样例99",
    "gender": "女",
    "dob": "1/99/1990",
    "gangwei": "工程师",
    "start_date": "2019/08/01",
    "zuihao_xueli": "大学本科",
    "title": "工程师",
    "skill": "高级工（配电线路工）",
    "level": "三级"
  },
  {
    "id": "100",
    "danwei": "宝应公司",
    "bumen": "配电运检中心（项目管理分中心）",
    "banzu_name": "配电运检班",
    "banzu_type": "配电运检",
    "name": "样例100",
    "gender": "男",
    "dob": "1/100/1990",
    "gangwei": "见习岗",
    "start_date": "2010/08/01",
    "zuihao_xueli": "硕士研究生",
    "title": "助理工程师",
    "skill": "技师（配电线路工）",
    "level": "四级"
  },
  {
    "id": "101",
    "danwei": "宝应公司",
    "bumen": "配电运检中心（项目管理分中心）",
    "banzu_name": "配电运检班",
    "banzu_type": "配电运检",
    "name": "谢德俊",
    "gender": "男",
    "dob": "8/12/00",
    "gangwei": "见习岗",
    "start_date": "2024/08/05",
    "zuihao_xueli": "大学本科",
    "title": "",
    "skill": "",
    "level": ""
  },
  {
    "id": "102",
    "danwei": "宝应公司",
    "bumen": "配电运检中心（项目管理分中心）",
    "banzu_name": "配电运检班",
    "banzu_type": "配电运检",
    "name": "张致昊",
    "gender": "男",
    "dob": "2/5/99",
    "gangwei": "配电运检助理",
    "start_date": "2023/08/07",
    "zuihao_xueli": "硕士研究生",
    "title": "助理工程师",
    "skill": "中级工（配电线路工）",
    "level": "四级"
  },
  {
    "id": "103",
    "danwei": "宝应公司",
    "bumen": "配电运检中心（项目管理分中心）",
    "banzu_name": "配电运检班",
    "banzu_type": "配电运检",
    "name": "高兴",
    "gender": "男",
    "dob": "3/29/00",
    "gangwei": "配电运检助理",
    "start_date": "2023/08/07",
    "zuihao_xueli": "大学本科",
    "title": "助理工程师",
    "skill": "中级工（配电线路工）",
    "level": "四级"
  },
  {
    "id": "104",
    "danwei": "宝应公司",
    "bumen": "配电运检中心（项目管理分中心）",
    "banzu_name": "配电运检班",
    "banzu_type": "配电运检",
    "name": "朱德月",
    "gender": "男",
    "dob": "8/9/00",
    "gangwei": "配电运检员",
    "start_date": "2022/08/01",
    "zuihao_xueli": "大学本科",
    "title": "助理工程师",
    "skill": "中级工（配电线路工）",
    "level": "四级"
  },
  {
    "id": "105",
    "danwei": "宝应公司",
    "bumen": "配电运检中心（项目管理分中心）",
    "banzu_name": "配电运检班",
    "banzu_type": "配电运检",
    "name": "王燕",
    "gender": "女",
    "dob": "10/31/96",
    "gangwei": "配电运检师",
    "start_date": "2019/08/01",
    "zuihao_xueli": "大学本科",
    "title": "助理工程师",
    "skill": "高级工（配电线路工）",
    "level": "三级"
  },
  {
    "id": "106",
    "danwei": "宝应公司",
    "bumen": "配电运检中心（项目管理分中心）",
    "banzu_name": "配电运检班",
    "banzu_type": "配电运检",
    "name": "王璐",
    "gender": "女",
    "dob": "12/28/97",
    "gangwei": "配电运检师",
    "start_date": "2021/10/08",
    "zuihao_xueli": "大学本科",
    "title": "助理工程师",
    "skill": "高级工（配电线路工）",
    "level": "三级"
  }
]
